poeem/__init__.py
poeem/ops/bin/__init__.py
poeem/ops/bin/clustering_op.so
poeem/ops/bin/clustering_raw_op.so
poeem/ops/bin/combinatorial_op.so
poeem/ops/bin/pqknn_dataset_op.so
poeem/ops/bin/rec_dataset_op.so
poeem/ops/bin/search_op.so
poeem/ops/bin/tokenizer_op.so
poeem/ops/cpp/clustering_op.cc
poeem/ops/cpp/clustering_raw_op.cc
poeem/ops/cpp/combinatorial_op.cc
poeem/ops/cpp/pqknn_dataset_op.cc
poeem/ops/cpp/pqknn_dataset_op.h
poeem/ops/cpp/rec_dataset_op.cc
poeem/ops/cpp/search_op.cc
poeem/ops/cpp/tokenizer_op.cc
poeem/ops/cpp/vector_util.h
poeem/ops/python/__init__.py
poeem/ops/python/clustering.py
poeem/ops/python/combinatorics.py
poeem/ops/python/encode.py
poeem/ops/python/indexing.py
poeem/ops/python/pqknn_dataset.py
poeem/ops/python/rec_dataset.py
poeem/ops/python/search.py
poeem/ops/python/tokenizer.py
poeem/python/__init__.py
poeem/python/embedding.py
poeem-1.2.1.dist-info/METADATA
poeem-1.2.1.dist-info/WHEEL
poeem-1.2.1.dist-info/top_level.txt
poeem-1.2.1.dist-info/RECORD
